pylang_annotations/__init__.py
pylang_annotations/__init__.pyi
pylang_annotations-0.0.14.dist-info/LICENSE
pylang_annotations-0.0.14.dist-info/METADATA
pylang_annotations-0.0.14.dist-info/WHEEL
pylang_annotations-0.0.14.dist-info/top_level.txt
pylang_annotations-0.0.14.dist-info/RECORD
