Metadata-Version: 2.1
Name: pylang_annotations
Version: 0.0.14
Summary: The annotations for Pylang project.
Author-email: xia__mc <xiayichun0512@gmail.com>
Project-URL: Homepage, https://github.com/xia-mc/Pylang
Project-URL: Issues, https://github.com/xia-mc/Pylang/issues
Classifier: Programming Language :: Python :: 3
Classifier: License :: OSI Approved :: MIT License
Classifier: Operating System :: OS Independent
Requires-Python: >=3.7
License-File: LICENSE
